pysastra/Tokenizer.py
pysastra/__init__.py
pysastra/utils.py
pysastra-0.1.0.dist-info/LICENSE
pysastra-0.1.0.dist-info/METADATA
pysastra-0.1.0.dist-info/WHEEL
pysastra-0.1.0.dist-info/top_level.txt
pysastra-0.1.0.dist-info/RECORD
