Metadata-Version: 2.1
Name: pysastra
Version: 0.1.0
Summary: Lightweight Natural Language Processing for Indonesian Language.
Home-page: https://github.com/sastra-id/pysastra
Author: Fahmi Rasyid
Author-email: ufarasfa@gmail.com
License: MIT
Platform: UNKNOWN
Requires-Python: >=3.6.3
Requires-Dist: nose
